strategais/__init__.py
strategais/__main__.py
strategais/llm_tools.py
strategais/save_tools.py
strategais/templates/index.html
strategais-0.2.12.dist-info/LICENSE
strategais-0.2.12.dist-info/METADATA
strategais-0.2.12.dist-info/WHEEL
strategais-0.2.12.dist-info/top_level.txt
strategais-0.2.12.dist-info/RECORD
