Metadata-Version: 2.1
Name: strategais
Version: 0.2.12
Summary: A Python library for deploying large language models (LLMs) in local environments.
License-File: LICENSE
Requires-Dist: fastapi
Requires-Dist: fastapi-utils
Requires-Dist: uvicorn
Requires-Dist: starlette
Requires-Dist: websockets
Requires-Dist: flask
Requires-Dist: numpy
Requires-Dist: pandas
Requires-Dist: requests
Requires-Dist: scikit-learn
Requires-Dist: scipy
Requires-Dist: SQLAlchemy
Requires-Dist: pydantic
Requires-Dist: aiofiles
Requires-Dist: psycopg2-binary
Requires-Dist: email-validator
Requires-Dist: jinja2
Requires-Dist: python-multipart
Requires-Dist: httpx
Requires-Dist: sse-starlette
Requires-Dist: langchain
Requires-Dist: python-dotenv
Requires-Dist: huggingface-hub
Requires-Dist: chromadb
Requires-Dist: redis
Requires-Dist: sentence-transformers
Requires-Dist: unstructured
Requires-Dist: datasets
Requires-Dist: loralib
Requires-Dist: sentencepiece
Requires-Dist: transformers
Requires-Dist: pytorch-lightning
Requires-Dist: torch
Requires-Dist: accelerate
Requires-Dist: torchaudio
Requires-Dist: cryptography (==38.0.4)
Requires-Dist: xformers (==0.0.12)
Provides-Extra: ext
Requires-Dist: openai ; extra == 'ext'
Requires-Dist: boto3 ; extra == 'ext'
Requires-Dist: email-validator ; extra == 'ext'
Requires-Dist: watchdog[watchmedo] ; extra == 'ext'
